<?xml version="1.0" encoding="UTF-8" standalone="yes"?>
<w:footnotes xmlns:o="urn:schemas-microsoft-com:office:office" xmlns:r="http://schemas.openxmlformats.org/officeDocument/2006/relationships" xmlns:v="urn:schemas-microsoft-com:vml" xmlns:w="http://schemas.openxmlformats.org/wordprocessingml/2006/main" xmlns:w10="urn:schemas-microsoft-com:office:word" xmlns:wp="http://schemas.openxmlformats.org/drawingml/2006/wordprocessingDrawing" xmlns:pic="http://schemas.openxmlformats.org/drawingml/2006/picture" xmlns:wps="http://schemas.microsoft.com/office/word/2010/wordprocessingShape" xmlns:wpg="http://schemas.microsoft.com/office/word/2010/wordprocessingGroup" xmlns:mc="http://schemas.openxmlformats.org/markup-compatibility/2006" xmlns:wp14="http://schemas.microsoft.com/office/word/2010/wordprocessingDrawing" xmlns:w14="http://schemas.microsoft.com/office/word/2010/wordml" xmlns:w15="http://schemas.microsoft.com/office/word/2012/wordml" mc:Ignorable="w14 wp14 w15"><w:footnote w:id="0" w:type="separator"><w:p><w:pPr><w:rPr><w:sz w:val="13"/></w:rPr></w:pPr><w:r><w:separator/></w:r></w:p></w:footnote><w:footnote w:id="1" w:type="continuationSeparator"><w:p><w:pPr><w:rPr><w:sz w:val="13"/></w:rPr></w:pPr><w:r><w:continuationSeparator/></w:r></w:p></w:footnote><w:footnote w:id="2"><w:p><w:pPr><w:pStyle w:val="FootnoteText"/><w:rPr><w:rFonts w:cs="Noto Rashi Hebrew"/><w:b/><w:bCs/></w:rPr></w:pPr><w:r><w:rPr><w:rStyle w:val="FootnoteCharacters"/></w:rPr><w:footnoteRef/></w:r><w:r><w:rPr><w:rFonts w:cs="Noto Rashi Hebrew"/><w:b/><w:b/><w:bCs/><w:rtl w:val="true"/></w:rPr><w:tab/><w:t>משנה ג</w:t></w:r><w:r><w:rPr><w:rFonts w:cs="Noto Rashi Hebrew"/><w:b/><w:bCs/><w:rtl w:val="true"/></w:rPr><w:t>:</w:t></w:r></w:p></w:footnote><w:footnote w:id="3"><w:p><w:pPr><w:pStyle w:val="FootnoteText"/><w:rPr><w:rFonts w:cs="Noto Rashi Hebrew"/></w:rPr></w:pPr><w:r><w:rPr><w:rStyle w:val="FootnoteCharacters"/></w:rPr><w:footnoteRef/></w:r><w:r><w:rPr><w:rFonts w:cs="Noto Rashi Hebrew"/><w:b w:val="false"/><w:b w:val="false"/><w:bCs w:val="false"/><w:rtl w:val="true"/></w:rPr><w:tab/><w:t>מן הגמרא</w:t></w:r><w:r><w:rPr><w:rFonts w:cs="Noto Rashi Hebrew"/><w:b w:val="false"/><w:bCs w:val="false"/><w:rtl w:val="true"/></w:rPr><w:t xml:space="preserve">, </w:t></w:r><w:r><w:rPr><w:rFonts w:cs="Noto Rashi Hebrew"/><w:b w:val="false"/><w:b w:val="false"/><w:bCs w:val="false"/><w:rtl w:val="true"/></w:rPr><w:t>ייצא שלש שיטות בזה</w:t></w:r><w:r><w:rPr><w:rFonts w:cs="Noto Rashi Hebrew"/><w:b w:val="false"/><w:bCs w:val="false"/><w:rtl w:val="true"/></w:rPr><w:t xml:space="preserve">, </w:t></w:r><w:r><w:rPr><w:rFonts w:cs="Noto Rashi Hebrew"/><w:b w:val="false"/><w:b w:val="false"/><w:bCs w:val="false"/><w:rtl w:val="true"/></w:rPr><w:t>ולא רק שנים שבמשנתינו</w:t></w:r><w:r><w:rPr><w:rFonts w:cs="Noto Rashi Hebrew"/><w:b w:val="false"/><w:bCs w:val="false"/><w:rtl w:val="true"/></w:rPr><w:t xml:space="preserve">. </w:t></w:r><w:r><w:rPr><w:rFonts w:cs="Noto Rashi Hebrew"/><w:b w:val="false"/><w:b w:val="false"/><w:bCs w:val="false"/><w:rtl w:val="true"/></w:rPr><w:t>בע”ה</w:t></w:r><w:r><w:rPr><w:rFonts w:cs="Noto Rashi Hebrew"/><w:b w:val="false"/><w:bCs w:val="false"/><w:rtl w:val="true"/></w:rPr><w:t xml:space="preserve">, </w:t></w:r><w:r><w:rPr><w:rFonts w:cs="Noto Rashi Hebrew"/><w:b w:val="false"/><w:b w:val="false"/><w:bCs w:val="false"/><w:rtl w:val="true"/></w:rPr><w:t xml:space="preserve">נבאר את זה בהשלמות </w:t></w:r><w:r><w:rPr><w:rFonts w:cs="Noto Rashi Hebrew"/><w:b w:val="false"/><w:bCs w:val="false"/><w:rtl w:val="true"/></w:rPr><w:t>[</w:t></w:r><w:r><w:rPr><w:rFonts w:cs="Noto Rashi Hebrew"/><w:b w:val="false"/><w:b w:val="false"/><w:bCs w:val="false"/><w:rtl w:val="true"/></w:rPr><w:t>א</w:t></w:r><w:r><w:rPr><w:rFonts w:cs="Noto Rashi Hebrew"/><w:b w:val="false"/><w:bCs w:val="false"/><w:rtl w:val="true"/></w:rPr><w:t>].</w:t></w:r></w:p></w:footnote><w:footnote w:id="4"><w:p><w:pPr><w:pStyle w:val="FootnoteText"/><w:rPr><w:rFonts w:cs="Noto Rashi Hebrew"/></w:rPr></w:pPr><w:r><w:rPr><w:rStyle w:val="FootnoteCharacters"/></w:rPr><w:footnoteRef/></w:r><w:r><w:rPr><w:rFonts w:cs="Noto Rashi Hebrew"/><w:rtl w:val="true"/></w:rPr><w:tab/><w:t>גמרא דורש את זה ממש</w:t></w:r><w:r><w:rPr><w:rFonts w:cs="Noto Rashi Hebrew"/><w:rtl w:val="true"/></w:rPr><w:t>&quot;</w:t></w:r><w:r><w:rPr><w:rFonts w:cs="Noto Rashi Hebrew"/><w:rtl w:val="true"/></w:rPr><w:t>כ</w:t></w:r><w:r><w:rPr><w:rFonts w:cs="Noto Rashi Hebrew"/><w:rtl w:val="true"/></w:rPr><w:t>, &quot;</w:t></w:r><w:r><w:rPr><w:rFonts w:cs="Noto Rashi Hebrew"/><w:rtl w:val="true"/></w:rPr><w:t>שמע</w:t></w:r><w:r><w:rPr><w:rFonts w:cs="Noto Rashi Hebrew"/><w:rtl w:val="true"/></w:rPr><w:t xml:space="preserve">.&quot; </w:t></w:r><w:r><w:rPr><w:rFonts w:cs="Noto Rashi Hebrew"/><w:b/><w:bCs/><w:u w:val="single"/><w:rtl w:val="true"/></w:rPr><w:t>(</w:t></w:r><w:r><w:rPr><w:rFonts w:cs="Noto Rashi Hebrew"/><w:b/><w:b/><w:bCs/><w:u w:val="single"/><w:rtl w:val="true"/></w:rPr><w:t>טו</w:t></w:r><w:r><w:rPr><w:rFonts w:cs="Noto Rashi Hebrew"/><w:b/><w:bCs/><w:u w:val="single"/><w:rtl w:val="true"/></w:rPr><w:t>.)</w:t></w:r><w:r><w:rPr><w:rFonts w:cs="Noto Rashi Hebrew"/><w:b w:val="false"/><w:bCs w:val="false"/><w:u w:val="none"/><w:rtl w:val="true"/></w:rPr><w:t xml:space="preserve"> [</w:t></w:r><w:r><w:rPr><w:rFonts w:cs="Noto Rashi Hebrew"/><w:b w:val="false"/><w:b w:val="false"/><w:bCs w:val="false"/><w:u w:val="none"/><w:rtl w:val="true"/></w:rPr><w:t>ב</w:t></w:r><w:r><w:rPr><w:rFonts w:cs="Noto Rashi Hebrew"/><w:b w:val="false"/><w:bCs w:val="false"/><w:u w:val="none"/><w:rtl w:val="true"/></w:rPr><w:t>]</w:t></w:r></w:p></w:footnote><w:footnote w:id="5"><w:p><w:pPr><w:pStyle w:val="FootnoteText"/><w:rPr><w:rFonts w:cs="Noto Rashi Hebrew"/></w:rPr></w:pPr><w:r><w:rPr><w:rStyle w:val="FootnoteCharacters"/></w:rPr><w:footnoteRef/></w:r><w:r><w:rPr><w:rFonts w:cs="Noto Rashi Hebrew"/><w:rtl w:val="true"/></w:rPr><w:tab/><w:t xml:space="preserve">פוסק גמרא </w:t></w:r><w:r><w:rPr><w:rFonts w:cs="Noto Rashi Hebrew"/><w:b/><w:bCs/><w:u w:val="single"/><w:rtl w:val="true"/></w:rPr><w:t>(</w:t></w:r><w:r><w:rPr><w:rFonts w:cs="Noto Rashi Hebrew"/><w:b/><w:b/><w:bCs/><w:u w:val="single"/><w:rtl w:val="true"/></w:rPr><w:t>טו</w:t></w:r><w:r><w:rPr><w:rFonts w:cs="Noto Rashi Hebrew"/><w:b/><w:bCs/><w:u w:val="single"/><w:rtl w:val="true"/></w:rPr><w:t>:</w:t></w:r><w:r><w:rPr><w:rFonts w:cs="Noto Rashi Hebrew"/><w:b/><w:bCs/><w:u w:val="single"/><w:rtl w:val="true"/></w:rPr><w:t>)</w:t></w:r><w:r><w:rPr><w:rFonts w:cs="Noto Rashi Hebrew"/><w:rtl w:val="true"/></w:rPr><w:t xml:space="preserve"> </w:t></w:r><w:r><w:rPr><w:rFonts w:cs="Noto Rashi Hebrew"/><w:rtl w:val="true"/></w:rPr><w:t>כתנא קמא</w:t></w:r><w:r><w:rPr><w:rFonts w:cs="Noto Rashi Hebrew"/><w:rtl w:val="true"/></w:rPr><w:t>.</w:t></w:r></w:p></w:footnote><w:footnote w:id="6"><w:p><w:pPr><w:pStyle w:val="FootnoteText"/><w:rPr><w:rFonts w:cs="Noto Rashi Hebrew"/></w:rPr></w:pPr><w:r><w:rPr><w:rStyle w:val="FootnoteCharacters"/></w:rPr><w:footnoteRef/></w:r><w:r><w:rPr><w:rFonts w:cs="Noto Rashi Hebrew"/><w:rtl w:val="true"/></w:rPr><w:tab/><w:t>רש</w:t></w:r><w:r><w:rPr><w:rFonts w:cs="Noto Rashi Hebrew"/><w:rtl w:val="true"/></w:rPr><w:t>&quot;</w:t></w:r><w:r><w:rPr><w:rFonts w:cs="Noto Rashi Hebrew"/><w:rtl w:val="true"/></w:rPr><w:t xml:space="preserve">י מפרש שהוא </w:t></w:r><w:r><w:rPr><w:rFonts w:cs="Noto Rashi Hebrew"/><w:rtl w:val="true"/></w:rPr><w:t xml:space="preserve">לפרשן יפה בשפתי </w:t></w:r><w:r><w:rPr><w:rFonts w:cs="Noto Rashi Hebrew"/><w:rtl w:val="true"/></w:rPr><w:t>(</w:t></w:r><w:r><w:rPr><w:rFonts w:cs="Noto Rashi Hebrew"/><w:rtl w:val="true"/></w:rPr><w:t>רש</w:t></w:r><w:r><w:rPr><w:rFonts w:cs="Noto Rashi Hebrew"/><w:rtl w:val="true"/></w:rPr><w:t>&quot;</w:t></w:r><w:r><w:rPr><w:rFonts w:cs="Noto Rashi Hebrew"/><w:rtl w:val="true"/></w:rPr><w:t xml:space="preserve">י </w:t></w:r><w:r><w:rPr><w:rFonts w:cs="Noto Rashi Hebrew"/><w:b/><w:b/><w:bCs/><w:rtl w:val="true"/></w:rPr><w:t>טו</w:t></w:r><w:r><w:rPr><w:rFonts w:cs="Noto Rashi Hebrew"/><w:b/><w:bCs/><w:rtl w:val="true"/></w:rPr><w:t>.</w:t></w:r><w:r><w:rPr><w:rFonts w:cs="Noto Rashi Hebrew"/><w:rtl w:val="true"/></w:rPr><w:t xml:space="preserve">). </w:t></w:r><w:r><w:rPr><w:rFonts w:cs="Noto Rashi Hebrew"/><w:rtl w:val="true"/></w:rPr><w:t xml:space="preserve">עיין בהשלמות </w:t></w:r><w:r><w:rPr><w:rFonts w:cs="Noto Rashi Hebrew"/><w:rtl w:val="true"/></w:rPr><w:t>[</w:t></w:r><w:r><w:rPr><w:rFonts w:cs="Noto Rashi Hebrew"/><w:rtl w:val="true"/></w:rPr><w:t>ג</w:t></w:r><w:r><w:rPr><w:rFonts w:cs="Noto Rashi Hebrew"/><w:rtl w:val="true"/></w:rPr><w:t>].</w:t></w:r></w:p></w:footnote><w:footnote w:id="7"><w:p><w:pPr><w:pStyle w:val="FootnoteText"/><w:rPr><w:rFonts w:cs="Noto Rashi Hebrew"/></w:rPr></w:pPr><w:r><w:rPr><w:rStyle w:val="FootnoteCharacters"/></w:rPr><w:footnoteRef/></w:r><w:r><w:rPr><w:rFonts w:cs="Noto Rashi Hebrew"/><w:rtl w:val="true"/></w:rPr><w:tab/><w:t xml:space="preserve">גמרא </w:t></w:r><w:r><w:rPr><w:rFonts w:cs="Noto Rashi Hebrew"/><w:rtl w:val="true"/></w:rPr><w:t>(</w:t></w:r><w:r><w:rPr><w:rFonts w:cs="Noto Rashi Hebrew"/><w:rtl w:val="true"/></w:rPr><w:t>טו</w:t></w:r><w:r><w:rPr><w:rFonts w:cs="Noto Rashi Hebrew"/><w:rtl w:val="true"/></w:rPr><w:t xml:space="preserve">:) </w:t></w:r><w:r><w:rPr><w:rFonts w:cs="Noto Rashi Hebrew"/><w:rtl w:val="true"/></w:rPr><w:t>דורש את זה מ</w:t></w:r><w:r><w:rPr><w:rFonts w:cs="Noto Rashi Hebrew"/><w:rtl w:val="true"/></w:rPr><w:t>&quot;</w:t></w:r><w:r><w:rPr><w:rFonts w:cs="Noto Rashi Hebrew"/><w:rtl w:val="true"/></w:rPr><w:t>ולמדתם</w:t></w:r><w:r><w:rPr><w:rFonts w:cs="Noto Rashi Hebrew"/><w:rtl w:val="true"/></w:rPr><w:t>.” [</w:t></w:r><w:r><w:rPr><w:rFonts w:cs="Noto Rashi Hebrew"/><w:rtl w:val="true"/></w:rPr><w:t>ד</w:t></w:r><w:r><w:rPr><w:rFonts w:cs="Noto Rashi Hebrew"/><w:rtl w:val="true"/></w:rPr><w:t>]</w:t></w:r></w:p></w:footnote><w:footnote w:id="8"><w:p><w:pPr><w:pStyle w:val="FootnoteText"/><w:rPr><w:rFonts w:cs="Noto Rashi Hebrew"/></w:rPr></w:pPr><w:r><w:rPr><w:rStyle w:val="FootnoteCharacters"/></w:rPr><w:footnoteRef/></w:r><w:r><w:rPr><w:rFonts w:cs="Noto Rashi Hebrew"/><w:rtl w:val="true"/></w:rPr><w:tab/><w:t xml:space="preserve">פוסק גמרא </w:t></w:r><w:r><w:rPr><w:rFonts w:cs="Noto Rashi Hebrew"/><w:b/><w:bCs/><w:u w:val="single"/><w:rtl w:val="true"/></w:rPr><w:t>(</w:t></w:r><w:r><w:rPr><w:rFonts w:cs="Noto Rashi Hebrew"/><w:b/><w:b/><w:bCs/><w:u w:val="single"/><w:rtl w:val="true"/></w:rPr><w:t>טו</w:t></w:r><w:r><w:rPr><w:rFonts w:cs="Noto Rashi Hebrew"/><w:b/><w:bCs/><w:u w:val="single"/><w:rtl w:val="true"/></w:rPr><w:t>:)</w:t></w:r><w:r><w:rPr><w:rFonts w:cs="Noto Rashi Hebrew"/><w:rtl w:val="true"/></w:rPr><w:t xml:space="preserve"> </w:t></w:r><w:r><w:rPr><w:rFonts w:cs="Noto Rashi Hebrew"/><w:rtl w:val="true"/></w:rPr><w:t>כרבי יוסי</w:t></w:r><w:r><w:rPr><w:rFonts w:cs="Noto Rashi Hebrew"/><w:rtl w:val="true"/></w:rPr><w:t>.</w:t></w:r></w:p></w:footnote><w:footnote w:id="9"><w:p><w:pPr><w:pStyle w:val="FootnoteText"/><w:rPr><w:rFonts w:cs="Noto Rashi Hebrew"/></w:rPr></w:pPr><w:r><w:rPr><w:rStyle w:val="FootnoteCharacters"/></w:rPr><w:footnoteRef/></w:r><w:r><w:rPr><w:rFonts w:cs="Noto Rashi Hebrew"/><w:rtl w:val="true"/></w:rPr><w:tab/><w:t>[</w:t></w:r><w:r><w:rPr><w:rFonts w:cs="Noto Rashi Hebrew"/><w:rtl w:val="true"/></w:rPr><w:t>ד</w:t></w:r><w:r><w:rPr><w:rFonts w:cs="Noto Rashi Hebrew"/><w:rtl w:val="true"/></w:rPr><w:t>]</w:t></w:r></w:p></w:footnote><w:footnote w:id="10"><w:p><w:pPr><w:pStyle w:val="FootnoteText"/><w:rPr><w:rFonts w:cs="Noto Rashi Hebrew"/></w:rPr></w:pPr><w:r><w:rPr><w:rStyle w:val="FootnoteCharacters"/></w:rPr><w:footnoteRef/></w:r><w:r><w:rPr><w:rFonts w:cs="Noto Rashi Hebrew"/><w:rtl w:val="true"/></w:rPr><w:tab/><w:t>ר</w:t></w:r><w:r><w:rPr><w:rFonts w:cs="Noto Rashi Hebrew"/><w:rtl w:val="true"/></w:rPr><w:t>&quot;</w:t></w:r><w:r><w:rPr><w:rFonts w:cs="Noto Rashi Hebrew"/><w:rtl w:val="true"/></w:rPr><w:t>ל</w:t></w:r><w:r><w:rPr><w:rFonts w:cs="Noto Rashi Hebrew"/><w:rtl w:val="true"/></w:rPr><w:t xml:space="preserve">, </w:t></w:r><w:r><w:rPr><w:rFonts w:cs="Noto Rashi Hebrew"/><w:rtl w:val="true"/></w:rPr><w:t>שאמר מילה מאוחרת קודם מילה מוקדמת</w:t></w:r><w:r><w:rPr><w:rFonts w:cs="Noto Rashi Hebrew"/><w:rtl w:val="true"/></w:rPr><w:t xml:space="preserve">. </w:t></w:r><w:r><w:rPr><w:rFonts w:cs="Noto Rashi Hebrew"/><w:b/><w:bCs/><w:rtl w:val="true"/></w:rPr><w:t>(</w:t></w:r><w:r><w:rPr><w:rFonts w:cs="Noto Rashi Hebrew"/><w:rtl w:val="true"/></w:rPr><w:t>רש</w:t></w:r><w:r><w:rPr><w:rFonts w:cs="Noto Rashi Hebrew"/><w:rtl w:val="true"/></w:rPr><w:t>&quot;</w:t></w:r><w:r><w:rPr><w:rFonts w:cs="Noto Rashi Hebrew"/><w:rtl w:val="true"/></w:rPr><w:t xml:space="preserve">י </w:t></w:r><w:r><w:rPr><w:rFonts w:cs="Noto Rashi Hebrew"/><w:b/><w:b/><w:bCs/><w:rtl w:val="true"/></w:rPr><w:t>יג</w:t></w:r><w:r><w:rPr><w:rFonts w:cs="Noto Rashi Hebrew"/><w:b/><w:bCs/><w:rtl w:val="true"/></w:rPr><w:t>.</w:t></w:r><w:r><w:rPr><w:rFonts w:cs="Noto Rashi Hebrew"/><w:rtl w:val="true"/></w:rPr><w:t>)</w:t></w:r></w:p></w:footnote><w:footnote w:id="11"><w:p><w:pPr><w:pStyle w:val="FootnoteText"/><w:rPr><w:rFonts w:cs="Noto Rashi Hebrew"/></w:rPr></w:pPr><w:r><w:rPr><w:rStyle w:val="FootnoteCharacters"/></w:rPr><w:footnoteRef/></w:r><w:r><w:rPr><w:rFonts w:cs="Noto Rashi Hebrew"/><w:rtl w:val="true"/></w:rPr><w:tab/><w:t>חולקים רבי ורבנן מהו המקור לזה</w:t></w:r><w:r><w:rPr><w:rFonts w:cs="Noto Rashi Hebrew"/><w:rtl w:val="true"/></w:rPr><w:t xml:space="preserve">. </w:t></w:r><w:r><w:rPr><w:rFonts w:cs="Noto Rashi Hebrew"/><w:rtl w:val="true"/></w:rPr><w:t>רבי דורש אותו מ</w:t></w:r><w:r><w:rPr><w:rFonts w:cs="Noto Rashi Hebrew"/><w:rtl w:val="true"/></w:rPr><w:t>&quot;</w:t></w:r><w:r><w:rPr><w:rFonts w:cs="Noto Rashi Hebrew"/><w:rtl w:val="true"/></w:rPr><w:t>ה</w:t></w:r><w:r><w:rPr><w:rFonts w:cs="Noto Rashi Hebrew"/><w:rtl w:val="true"/></w:rPr><w:t xml:space="preserve">&quot; </w:t></w:r><w:r><w:rPr><w:rFonts w:cs="Noto Rashi Hebrew"/><w:rtl w:val="true"/></w:rPr><w:t xml:space="preserve">של </w:t></w:r><w:r><w:rPr><w:rFonts w:cs="Noto Rashi Hebrew"/><w:rtl w:val="true"/></w:rPr><w:t>&quot;</w:t></w:r><w:r><w:rPr><w:rFonts w:cs="Noto Rashi Hebrew"/><w:rtl w:val="true"/></w:rPr><w:t>הדברים</w:t></w:r><w:r><w:rPr><w:rFonts w:cs="Noto Rashi Hebrew"/><w:rtl w:val="true"/></w:rPr><w:t xml:space="preserve">.” </w:t></w:r><w:r><w:rPr><w:rFonts w:cs="Noto Rashi Hebrew"/><w:rtl w:val="true"/></w:rPr><w:t>רבנן דורשים אותו מ</w:t></w:r><w:r><w:rPr><w:rFonts w:cs="Noto Rashi Hebrew"/><w:rtl w:val="true"/></w:rPr><w:t>&quot;</w:t></w:r><w:r><w:rPr><w:rFonts w:cs="Noto Rashi Hebrew"/><w:rtl w:val="true"/></w:rPr><w:t>והיו</w:t></w:r><w:r><w:rPr><w:rFonts w:cs="Noto Rashi Hebrew"/><w:rtl w:val="true"/></w:rPr><w:t xml:space="preserve">.” </w:t></w:r><w:r><w:rPr><w:rFonts w:cs="Noto Rashi Hebrew"/><w:b/><w:bCs/><w:rtl w:val="true"/></w:rPr><w:t>(</w:t></w:r><w:r><w:rPr><w:rFonts w:cs="Noto Rashi Hebrew"/><w:b/><w:b/><w:bCs/><w:rtl w:val="true"/></w:rPr><w:t>יג</w:t></w:r><w:r><w:rPr><w:rFonts w:cs="Noto Rashi Hebrew"/><w:b/><w:bCs/><w:rtl w:val="true"/></w:rPr><w:t>.)</w:t></w:r></w:p></w:footnote><w:footnote w:id="12"><w:p><w:pPr><w:pStyle w:val="FootnoteText"/><w:rPr><w:rFonts w:cs="Noto Rashi Hebrew"/></w:rPr></w:pPr><w:r><w:rPr><w:rStyle w:val="FootnoteCharacters"/></w:rPr><w:footnoteRef/></w:r><w:r><w:rPr><w:rFonts w:cs="Noto Rashi Hebrew"/><w:rtl w:val="true"/></w:rPr><w:tab/><w:t>אם יודע שאמר דבר</w:t></w:r><w:r><w:rPr><w:rFonts w:cs="Noto Rashi Hebrew"/><w:rtl w:val="true"/></w:rPr><w:t xml:space="preserve">, </w:t></w:r><w:r><w:rPr><w:rFonts w:cs="Noto Rashi Hebrew"/><w:rtl w:val="true"/></w:rPr><w:t>אז חוזר למיד אחרי אותו דבר</w:t></w:r><w:r><w:rPr><w:rFonts w:cs="Noto Rashi Hebrew"/><w:rtl w:val="true"/></w:rPr><w:t xml:space="preserve">. </w:t></w:r><w:r><w:rPr><w:rFonts w:cs="Noto Rashi Hebrew"/><w:rtl w:val="true"/></w:rPr><w:t>אם לא יודע</w:t></w:r><w:r><w:rPr><w:rFonts w:cs="Noto Rashi Hebrew"/><w:rtl w:val="true"/></w:rPr><w:t xml:space="preserve">, </w:t></w:r><w:r><w:rPr><w:rFonts w:cs="Noto Rashi Hebrew"/><w:rtl w:val="true"/></w:rPr><w:t xml:space="preserve">חולקים ראשונים </w:t></w:r><w:r><w:rPr><w:rFonts w:cs="Noto Rashi Hebrew"/><w:rtl w:val="true"/></w:rPr><w:t>(</w:t></w:r><w:r><w:rPr><w:rFonts w:cs="Noto Rashi Hebrew"/><w:rtl w:val="true"/></w:rPr><w:t>מובאים בפני משה</w:t></w:r><w:r><w:rPr><w:rFonts w:cs="Noto Rashi Hebrew"/><w:rtl w:val="true"/></w:rPr><w:t xml:space="preserve">) </w:t></w:r><w:r><w:rPr><w:rFonts w:cs="Noto Rashi Hebrew"/><w:rtl w:val="true"/></w:rPr><w:t>אם חוזר לתחילת ”והיה</w:t></w:r><w:r><w:rPr><w:rFonts w:cs="Noto Rashi Hebrew"/><w:rtl w:val="true"/></w:rPr><w:t xml:space="preserve">,“ </w:t></w:r><w:r><w:rPr><w:rFonts w:cs="Noto Rashi Hebrew"/><w:rtl w:val="true"/></w:rPr><w:t>כיון שהוא ההפסק הראשון</w:t></w:r><w:r><w:rPr><w:rFonts w:cs="Noto Rashi Hebrew"/><w:rtl w:val="true"/></w:rPr><w:t xml:space="preserve">, </w:t></w:r><w:r><w:rPr><w:rFonts w:cs="Noto Rashi Hebrew"/><w:rtl w:val="true"/></w:rPr><w:t>ומצוי שיטעה שם</w:t></w:r><w:r><w:rPr><w:rFonts w:cs="Noto Rashi Hebrew"/><w:rtl w:val="true"/></w:rPr><w:t xml:space="preserve">, </w:t></w:r><w:r><w:rPr><w:rFonts w:cs="Noto Rashi Hebrew"/><w:rtl w:val="true"/></w:rPr><w:t>או חוזר לתחילת קריאת שמע</w:t></w:r><w:r><w:rPr><w:rFonts w:cs="Noto Rashi Hebrew"/><w:rtl w:val="true"/></w:rPr><w:t>.</w:t></w:r></w:p></w:footnote><w:footnote w:id="13"><w:p><w:pPr><w:pStyle w:val="FootnoteText"/><w:rPr><w:rFonts w:cs="Noto Rashi Hebrew"/></w:rPr></w:pPr><w:r><w:rPr><w:rStyle w:val="FootnoteCharacters"/></w:rPr><w:footnoteRef/></w:r><w:r><w:rPr><w:rFonts w:cs="Noto Rashi Hebrew"/><w:rtl w:val="true"/></w:rPr><w:tab/><w:t xml:space="preserve">גמרא </w:t></w:r><w:r><w:rPr><w:rFonts w:cs="Noto Rashi Hebrew"/><w:rtl w:val="true"/></w:rPr><w:t>(</w:t></w:r><w:r><w:rPr><w:rFonts w:cs="Noto Rashi Hebrew"/><w:b/><w:b/><w:bCs/><w:rtl w:val="true"/></w:rPr><w:t>טז</w:t></w:r><w:r><w:rPr><w:rFonts w:cs="Noto Rashi Hebrew"/><w:b/><w:bCs/><w:rtl w:val="true"/></w:rPr><w:t>.</w:t></w:r><w:r><w:rPr><w:rFonts w:cs="Noto Rashi Hebrew"/><w:rtl w:val="true"/></w:rPr><w:t xml:space="preserve">) </w:t></w:r><w:r><w:rPr><w:rFonts w:cs="Noto Rashi Hebrew"/><w:rtl w:val="true"/></w:rPr><w:t>מפרש שאין זה נוהג בין ”למען ירבו“ ו“אמת ויציב</w:t></w:r><w:r><w:rPr><w:rFonts w:cs="Noto Rashi Hebrew"/><w:rtl w:val="true"/></w:rPr><w:t xml:space="preserve">,“ </w:t></w:r><w:r><w:rPr><w:rFonts w:cs="Noto Rashi Hebrew"/><w:rtl w:val="true"/></w:rPr><w:t>שלא רגיל שיטעה שם</w:t></w:r><w:r><w:rPr><w:rFonts w:cs="Noto Rashi Hebrew"/><w:rtl w:val="true"/></w:rPr><w:t>. (</w:t></w:r><w:r><w:rPr><w:rFonts w:cs="Noto Rashi Hebrew"/><w:rtl w:val="true"/></w:rPr><w:t>כן מפ’ רש</w:t></w:r><w:r><w:rPr><w:rFonts w:cs="Noto Rashi Hebrew"/><w:rtl w:val="true"/></w:rPr><w:t>&quot;</w:t></w:r><w:r><w:rPr><w:rFonts w:cs="Noto Rashi Hebrew"/><w:rtl w:val="true"/></w:rPr><w:t>י שם</w:t></w:r><w:r><w:rPr><w:rFonts w:cs="Noto Rashi Hebrew"/><w:rtl w:val="true"/></w:rPr><w:t xml:space="preserve">, </w:t></w:r><w:r><w:rPr><w:rFonts w:cs="Noto Rashi Hebrew"/><w:rtl w:val="true"/></w:rPr><w:t>אבל נ“ל שיש ראשונים שכ’ שר</w:t></w:r><w:r><w:rPr><w:rFonts w:cs="Noto Rashi Hebrew"/><w:rtl w:val="true"/></w:rPr><w:t>&quot;</w:t></w:r><w:r><w:rPr><w:rFonts w:cs="Noto Rashi Hebrew"/><w:rtl w:val="true"/></w:rPr><w:t>ל שאם ממשיך בפיו</w:t></w:r><w:r><w:rPr><w:rFonts w:cs="Noto Rashi Hebrew"/><w:rtl w:val="true"/></w:rPr><w:t xml:space="preserve">, </w:t></w:r><w:r><w:rPr><w:rFonts w:cs="Noto Rashi Hebrew"/><w:rtl w:val="true"/></w:rPr><w:t>אף שאין מוחו יודע אם זה נכון</w:t></w:r><w:r><w:rPr><w:rFonts w:cs="Noto Rashi Hebrew"/><w:rtl w:val="true"/></w:rPr><w:t xml:space="preserve">, </w:t></w:r><w:r><w:rPr><w:rFonts w:cs="Noto Rashi Hebrew"/><w:rtl w:val="true"/></w:rPr><w:t>מניחים שהוא נכון</w:t></w:r><w:r><w:rPr><w:rFonts w:cs="Noto Rashi Hebrew"/><w:rtl w:val="true"/></w:rPr><w:t>.)</w:t></w:r></w:p></w:footnote></w:footnotes>